shelllikecui/__init__.py
shelllikecui/base.py
shelllikecui/cui.py
shelllikecui-0.0.2.dist-info/LICENSE
shelllikecui-0.0.2.dist-info/METADATA
shelllikecui-0.0.2.dist-info/WHEEL
shelllikecui-0.0.2.dist-info/top_level.txt
shelllikecui-0.0.2.dist-info/RECORD
