Metadata-Version: 2.1
Name: shelllikecui
Version: 0.0.2
Summary: shell like CUI
Author-email: userElaina <userelaina@pm.me>
Maintainer-email: userElaina <userelaina@pm.me>
License: MIT License
Project-URL: Homepage, https://github.com/userElaina/shell-like-cui
Project-URL: Bug Reports, https://github.com/userElaina/shell-like-cui/issues
Project-URL: Source, https://github.com/userElaina/shell-like-cui
Keywords: cui
Classifier: License :: OSI Approved :: MIT License
Classifier: Programming Language :: Python :: 3
Requires-Python: >=3.7
License-File: LICENSE
